geocrypt.py
geocrypt-0.1.1.dist-info/METADATA
geocrypt-0.1.1.dist-info/WHEEL
geocrypt-0.1.1.dist-info/top_level.txt
geocrypt-0.1.1.dist-info/RECORD
