Metadata-Version: 2.1
Name: geocrypt
Version: 0.1.1
Summary: Securely encode and decode hexadecimal with geometric figure.
Home-page: https://github.com/lolo859/geocrypt
Author: lolo859
Keywords: geocrypt geo crypt
Classifier: Natural Language :: English
Classifier: Operating System :: OS Independent
Classifier: Topic :: Security :: Cryptography
Requires-Dist: sympy >=1.13.3
